simplemt5/__init__.py
simplemt5/simplemt5.py
simplemt5-0.1.0.dist-info/LICENSE
simplemt5-0.1.0.dist-info/METADATA
simplemt5-0.1.0.dist-info/WHEEL
simplemt5-0.1.0.dist-info/top_level.txt
simplemt5-0.1.0.dist-info/RECORD
