Metadata-Version: 2.2
Name: simplemt5
Version: 0.1.0
Summary: Упрощенная библиотека для работы с MetaTrader 5
Home-page: https://github.com/yourusername/simplemt5
Author: SimpleMT5 Developer
Author-email: your.email@example.com
Classifier: Programming Language :: Python :: 3
Classifier: License :: OSI Approved :: MIT License
Classifier: Operating System :: OS Independent
Requires-Python: >=3.7
License-File: LICENSE
Requires-Dist: MetaTrader5>=5.0.0
Requires-Dist: pandas>=1.0.0
Requires-Dist: numpy>=1.18.0
Dynamic: author
Dynamic: author-email
Dynamic: classifier
Dynamic: description
Dynamic: description-content-type
Dynamic: home-page
Dynamic: requires-dist
Dynamic: requires-python
Dynamic: summary
